{
  "$schema": "http://json-schema.org/draft-07/schema#",
  "title": "Environment Variable",
  "description": "Bitrise Environment Variable",
  "type": "object",
  "maxProperties": 2,
  "minProperties": 1,
  "dependentSchemas": {
    "opts": {
      "minProperties": 2
    }
  },
  "additionalProperties": { "type":  ["string", "null"] },
  "properties": {
    "opts": {
      "type": "object",
      "additionalProperties": false,
      "if": {
        "properties": {
          "is_sensitive": {
            "const": true
          }
        }
      },
      "then": {
        "properties": {
          "is_expand": {
            "const": true
          }
        }
      },
      "properties": {
        "is_expand": {
          "type": "boolean"
        },
        "skip_if_empty": {
          "type": "boolean"
        },
        "title": {
          "type": "string"
        },
        "description": {
          "type": "string"
        },
        "summary": {
          "type": "string"
        },
        "category": {
          "type": "string"
        },
        "value_options": {
          "type": "array",
          "minItems": 2,
          "items": {
            "type": "string"
          }
        },
        "is_required": {
          "type": "boolean"
        },
        "is_dont_change_value": {
          "type": "boolean"
        },
        "is_template": {
          "type": "boolean"
        },
        "is_sensitive": {
          "type": "boolean"
        },
        "unset": {
          "type": "boolean"
        },
        "meta": {
          "type": "object"
        }
      }
    }
  }
}